five_timer/__init__.py
five_timer/main.py
five_timer/resources/pinout.jpg
five_timer/resources/waveforms.gif
five_timer-1.0.dist-info/METADATA
five_timer-1.0.dist-info/WHEEL
five_timer-1.0.dist-info/entry_points.txt
five_timer-1.0.dist-info/top_level.txt
five_timer-1.0.dist-info/RECORD
