Metadata-Version: 2.1
Name: five-timer
Version: 1.0
Summary: 555-Timer calculator
Home-page: UNKNOWN
Author: Edwin Mwiti
Author-email: emwiti658@gmail.com
License: UNKNOWN
Platform: UNKNOWN
Requires-Dist: Pillow
